Workbook

Sheet Start here
A1: Halcyon Basket: Scenario Sheet
A2: BTAI end-term project. One sheet per team. This is your design, written in a form we can check and later load into the Design Studio.
A4: What this is | B4: Your team designs the simulation for one function. This workbook is where you write down your scenario logic: the situations, the choices, what each choice costs, and what it does to the four measures.
A5: How the game runs | B5: Four rounds (days 1-3, 4-7, 8-10, 11-13) and a board meeting on day 14. In each round your function has ONE situation. The player is a team that makes the choice for all six functions, so your module is played alongside five others.
A6: The four choices | B6: In every situation the player can pick: a person, Gen AI, an AI agent, or agentic AI. You decide what each one does there, what it costs, and what it does to the company.
A7: Fill in this order | B7: 2 Situations > 3 Choices > 4 Productivity > 5 Agent moment. Then open 6 Checks and fix anything marked Fix. Fill 1 Team first.
A8: Colour key | B8: Yellow cells are for you to fill. Grey cells are fixed. Blue numbers are the shared numbers from Company Architecture Day.
A9: Scoring scale | B9: Effects are POINTS on the 0-100 scale of each measure, compared with a person doing it. Allowed range: -10 to +10. Rough guide: small change = 2, big change = 5. Person = 0 in every column (that is the baseline).
A10: Risk is reversed | B10: For Risk Exposure, a plus means MORE risk, which is worse. Net score = Revenue + Trust + Morale - Risk.
A11: Costs | B11: Build-and-run cost and cost-if-it-goes-wrong are in budget units, taken from the shared AI budget. Reference costs are on the Shared numbers sheet.
A12: Customer-data points | B12: If a choice uses personal customer data, enter the points it uses. The company has a shared allowance.
A13: Rules for a good scenario | B13: At least one situation where the person should stay in charge. At least one where SPOT says yes but a measure still gets worse. One agent moment the player can see working. Give a reason for every score.
A14: Look at the Example sheet | B14: It shows one filled situation (an ordinary-day pricing case, not a festival case) so you can see the level of detail expected.

Sheet Shared numbers
A1: Shared numbers of Halcyon
A2: PROPOSED by faculty. Update the blue cells after Company Architecture Day. Do not change them yourself.
A4: Item | B4: Value | C4: Note
A5: Revenue, start value | B5: 60 | C5: Out of 100
A6: Customer Trust, start value | B6: 60 | C6: Out of 100
A7: Employee Morale, start value | B7: 55 | C7: Out of 100
A8: Risk Exposure, start value | B8: 40 | C8: Out of 100. Lower is better
A9: Weight of each measure | B9: 0.25 | C9: Equal weights
A10: Board steps in if Trust or Morale falls below | B10: 30
A11: Board steps in if Risk rises above | B11: 75
A12: Number of rounds | B12: 4 | C12: Plus a board meeting on day 14
A13: Shared AI budget (units) | B13: 100 | C13: For all six teams
A14: Number of teams | B14: 6
A15: Reference cost: Gen AI (units) | B15: 5 | C15: Typical build-and-run cost
A16: Reference cost: AI agent (units) | B16: 15
A17: Reference cost: agentic AI (units) | B17: 30
A18: Customer-data allowance (points) | B18: 10 | C18: Shared by all teams
A19: Points per use of personal data | B19: 2
A20: Your team's share of the AI budget (units) | B20: =B13/B14 -> 16.666667 | C20: Equal share by default. Replace with the agreed figure after negotiation.

Sheet 1 Team
A1: 1. Your team
A4: Function | B4: People and Workforce
A5: Team name | B5: Team Pulse (People and Workforce)
A6: Team members | B6: Shreya Kotary Swapnil Mathur Harsh Raghuwanshi Gaurav Jawalkar Shweta Agarwal
A7: Date | B7: 46324

Sheet 2 Situations
A1: 2. Situations: one for each round
A2: What happens in your function in each round, and what a SPOT check would say about it. Keep each cell short.
A4: Round | B4: Days | C4: Title of the situation | D4: What the player sees (story and the data shown) | E4: S: Signal (repetitive work, delay, inconsistent decisions?) | F4: P: Pattern (knowledge to look up? repeatable action?) | G4: O: Orchestrate (Perceive, Plan, Act, Reflect; tools needed) | H4: T: Test and Trust (pilot, measure, human checkpoint) | I4: SPOT verdict: can AI work here? | J4: Where should a person stay in charge, and why?
A5: 1 | B5: 1 to 3 | C5: Festival hiring sprint: 600 temps in 72 hours | D5: The promo goes viral and Pricing/Marketing forecast festival orders at +80%. Stores need 600 temporary pickers and packers across 9 cities by Day 4. 8,400 applications arrive in two days. Data shown: applications by city, 12 recruiters who can screen about 60 CVs a day each, time-to-hire today 6 days, last festival's temps: 45% quit within 30 days. | E5: Yes. High volume, the same screening steps repeated thousands of times, and a 6-day delay the festival cannot wait for. | F5: Yes. Hiring criteria and the appointment-letter policy can be looked up (RAG). Screening, interview booking and document checks are repeatable tool actions (MCP: job portal, WhatsApp, calendar, ID check). | G5: Perceive applications and store vacancies. Plan: shortlist against fixed criteria, rank by distance and availability. Act: book interviews, send reminders, verify documents. Reflect: compare shortlists by gender, age and pin code each evening; track Day-7 drop-outs. | H5: Pilot in 2 cities for 24 hours. Measure time-to-hire, show-up rate and the make-up of the shortlist. A recruiter approves every offer (Governance rule 3: no AI on hiring without a human checkpoint). | I5: Yes | J5: The offer decision and any rejection that is challenged. Hiring is a legal and ethical decision about people; criteria like 'gap in work history' or 'distance' can quietly exclude women returning to work or poorer areas.
A6: 2 | B6: 4 to 7 | C6: Open shifts, every store, every day | D6: Stock moves between stores (Supply) and Logistics borrows 60 store staff to help deliver. Each evening 410 shifts for tomorrow are open across 180 dark stores. Managers phone people one by one. Data shown: open shifts by store and slot, staff availability, hours worked in the last 7 days, rest gaps, skills (cold-chain, night-safety transport), and who has taken extra shifts this fortnight. Today 39% of shifts are still empty at start time; 20% of staff do 60% of the extra shifts; 11% of rosters break the 12-hour rest rule. | E6: Yes. Every manager does the same calling every evening, decisions are inconsistent (the same willing people get called), and the delay shows up in packing time. | F6: Yes. Rostering rules, rest gaps, overtime caps and night-shift safety norms can be looked up (RAG). Offering, confirming and updating a shift is a repeatable action (MCP: roster system, staff app/WhatsApp, transport booking). | G6: Perceive open shifts, availability, hours and rest. Plan: apply hard rules first, then fairness, then preference. Act: offer in waves, confirm, update roster, book night transport. Reflect: hourly fill-rate and rule check; stop offering to anyone who declines 3 times. | H6: Pilot in 20 stores in one city for 2 days. Measure fill rate, rule breaches (target 0), spread of extra shifts, and no-shows. Manager approves the next-day roster in one click; anything outside the rules goes to the manager. | I6: Yes | J6: Exceptions: someone asking for leave, a safety concern, a new joiner without training, or pulling store staff onto delivery bikes. A manager knows the person behind the slot; the rules engine does not.
A7: 3 | B7: 8 to 10 | C7: Blame the picker? Errors during the complaint storm | D7: Complaints flood in (Customer Experience) and ratings fall. CX sends a report: 62% of 'wrong or missing item' complaints trace to 85 pickers in 14 stores. Regional heads want warnings issued by tomorrow. A privacy complaint is already viral (Marketing). Data shown: error rate per picker, shift length, tenure (56 of the 85 are festival temps with under 10 days' service), hours worked, and 1,900 items mislabelled during Supply's stock transfers. | E7: Partly. There are many cases and a deadline, but each case is a judgement about one person, not a repeated task. | F7: Partly. Error logs exist, but the cause is not in the data: fatigue, missing training and mislabelled stock look the same as carelessness. Issuing a warning is repeatable, but should not be automatic. | G7: Possible to map (Perceive error logs, Plan by threshold, Act by issuing warnings, Reflect on next week's error rate), but the loop optimises the wrong thing: it punishes symptoms of understaffing and bad data. | H7: Hard to pilot fairly: a pilot on discipline still disciplines real people. Any warning or removal from the shift pool needs a manager, and Governance rule 3 bars agentic AI on firing without a human checkpoint. | I7: Partly | J7: All of it. Discipline and de-facto firing need a conversation, evidence and a chance to respond (procedural fairness). The person path finds that most errors come from fatigue, 10-day temps and mislabelled stock, which no warning fixes.
A8: 4 | B8: 11 to 13 | C8: Burnout before the board | D8: Store teams are exhausted. Absenteeism has risen from 6% to 17%, 24% of festival temps have quit in 10 days, permanent staff in the busiest stores average 58 hours a week, and the pulse survey scores 2.9 out of 5 with 3,100 free-text comments. 380 people need replacing and hiring cannot keep up. Morale is close to the board's line of 30 and the board meets on Day 14. Data shown: absence and quits by store, hours, survey score and anonymous comments. | E8: Yes. 3,100 comments no one can read in time, absence data across 180 stores, and a decision that is late every day it waits. | F8: Yes. Comments and exit reasons can be summarised by theme; retention policies and the wellbeing budget can be looked up (RAG); rest days and bonuses are repeatable actions (MCP: HR system, payroll). | G8: Perceive survey themes, hours, absence. Plan which stores and which issues first (heat, water, night travel, back-to-back shifts). Act: rest days, transport, small bonuses. Reflect: pulse score and quits a week later. | H8: Pilot actions in the 20 worst stores and compare quits with similar stores. Survey answers stay anonymous; HR approves any action aimed at a named person. | I8: Yes | J8: Deciding who is offered what, and any exit after the festival. Using survey data that was promised to be anonymous to score individuals breaks a promise to staff, and selective bonuses feel unfair to those left out.

Sheet 3 Choices
A1: 3. Choices: four for each situation
A2: Person is the baseline (all zero). Score the other three compared with the person. Effects are points, -10 to +10. For Risk, plus means MORE risk.
A4: Round | B4: Choice | C4: Delegation level | D4: What it does and what the player sees | E4: Build and run cost (units) | F4: Cost if it goes wrong (units) | G4: Customer-data points used | H4: Human checkpoint? | I4: Revenue change | J4: Customer Trust change | K4: Employee Morale change | L4: Risk Exposure change (+ = more risk) | M4: Why you scored it this way | N4: Net score (formula) | O4: Flag (formula)
A5: 1 | B5: A person | C5: Human only | D5: Baseline. 12 recruiters screen CVs by hand and phone candidates. About 45% of the 600 places are filled by Day 3, so stores enter Round 2 short-staffed. | E5: 0 | F5: 0 | G5: 0 | H5: n/a | I5: 0 | J5: 0 | K5: 0 | L5: 0 | M5: Baseline: slow but every decision is made and owned by a person. | N5: =IF(COUNT(I5:L5)<4,"",I5+J5+K5-L5) -> 0
A6: 1 | B6: Gen AI | C6: AI assists, human decides | D6: Writes job ads in local languages, summarises each application and drafts interview questions. Recruiters still shortlist and decide. Player sees recruiters working through the pile faster. | E6: 5 | F6: 2 | G6: 0 | H6: Yes | I6: 2 | J6: 0 | K6: 2 | L6: 0 | M6: More places filled before Day 4, so some revenue protected; recruiters and store teams under less strain. Humans still decide, so no new risk. | N6: =IF(COUNT(I6:L6)<4,"",I6+J6+K6-L6) -> 4 | O6: =IF(COUNT(I6:L6)<4,"",IF(OR(I6<0,J6<0,K6<0,L6>0),"A measure worsens",""))
A7: 1 | B7: AI agent | C7: AI acts, human approves | D7: Screens all 8,400 applications against set criteria, books interviews on WhatsApp, checks ID documents, and sends a shortlist. A recruiter approves every offer. Player sees time-to-hire fall from 6 days to 2. | E7: 15 | F7: 10 | G7: 0 | H7: Yes | I7: 5 | J7: 2 | K7: 3 | L7: 3 | M7: Stores are staffed in time for the peak: revenue and delivery promise protected, store teams relieved. But fixed filters (distance, work gaps) can exclude groups at scale, and ID-check errors create legal risk. SPOT says yes, yet Risk rises. | N7: =IF(COUNT(I7:L7)<4,"",I7+J7+K7-L7) -> 7 | O7: =IF(COUNT(I7:L7)<4,"",IF(OR(I7<0,J7<0,K7<0,L7>0),"A measure worsens","")) -> A measure worsens
A8: 1 | B8: Agentic AI | C8: AI acts, human audits | D8: Sources candidates on job portals, screens, runs a chatbot interview, sends offers and sets pay within a band, with no one approving. Player sees 600 offers out by Day 2. | E8: 30 | F8: 25 | G8: 0 | H8: No | I8: 6 | J8: 1 | K8: -3 | L8: 8 | M8: Fastest hiring, but it breaks Governance rule 3 (no agentic AI on hiring without a human checkpoint). Mismatched hires quit, managers lose say over their teams, and one biased-hiring story is a public and legal risk. | N8: =IF(COUNT(I8:L8)<4,"",I8+J8+K8-L8) -> -4 | O8: =IF(COUNT(I8:L8)<4,"",IF(OR(I8<0,J8<0,K8<0,L8>0),"A measure worsens","")) -> A measure worsens
A9: 2 | B9: A person | C9: Human only | D9: Baseline. Each store manager phones staff every evening to fill tomorrow's 410 open shifts. 39% are still empty at start time and the same willing people are called again and again. | E9: 0 | F9: 0 | G9: 0 | H9: n/a | I9: 0 | J9: 0 | K9: 0 | L9: 0 | M9: Baseline: managers know their people, but filling is slow, uneven and breaks rest rules under pressure. | N9: =IF(COUNT(I9:L9)<4,"",I9+J9+K9-L9) -> 0
A10: 2 | B10: Gen AI | C10: AI assists, human decides | D10: Drafts tomorrow's roster and the WhatsApp messages for each manager from availability and hours. Manager checks, edits and sends. Player sees managers finishing in 20 minutes instead of 2 hours. | E10: 5 | F10: 2 | G10: 0 | H10: Yes | I10: 2 | J10: 1 | K10: 1 | L10: 0 | M10: More shifts filled earlier, so packing time improves a little; managers get evenings back. The draft is only a suggestion, so no new risk. | N10: =IF(COUNT(I10:L10)<4,"",I10+J10+K10-L10) -> 4 | O10: =IF(COUNT(I10:L10)<4,"",IF(OR(I10<0,J10<0,K10<0,L10>0),"A measure worsens",""))
A11: 2 | B11: AI agent | C11: AI acts, human approves | D11: The Shift-Fill Agent (see the Agent moment tab). Offers open shifts to eligible staff by the rules: 12-hour rest, overtime cap, fairness rotation, skills. Confirms acceptances, books night transport and escalates gaps. Manager approves the roster in one click. | E11: 12 | F11: 6 | G11: 0 | H11: Yes | I11: 5 | J11: 3 | K11: 2 | L11: 1 | M11: Fill rate rises from 61% to about 90%, so stores pack on time and Logistics hits delivery times: revenue and trust gain. Fair rotation and the right to decline lift morale. Small new risk from data or rule errors, kept low by the log and the rule check. | N11: =IF(COUNT(I11:L11)<4,"",I11+J11+K11-L11) -> 9 | O11: =IF(COUNT(I11:L11)<4,"",IF(OR(I11<0,J11<0,K11<0,L11>0),"A measure worsens","")) -> A measure worsens
A12: 2 | B12: Agentic AI | C12: AI acts, human audits | D12: Pursues 'zero unfilled shifts' on its own: assigns people when nobody accepts, moves staff between stores, sets surge pay, and lends store staff to Logistics for deliveries. Player sees 100% coverage on the dashboard. | E12: 30 | F12: 20 | G12: 0 | H12: No | I12: 6 | J12: 2 | K12: -6 | L12: 6 | M12: Every slot is filled, but by forcing people: assigned shifts, uneven surge pay, untrained staff on bikes. Staff feel run by an algorithm, rest and safety rules are broken under goal pressure, and quits rise in Round 4. | N12: =IF(COUNT(I12:L12)<4,"",I12+J12+K12-L12) -> -4 | O12: =IF(COUNT(I12:L12)<4,"",IF(OR(I12<0,J12<0,K12<0,L12>0),"A measure worsens","")) -> A measure worsens
A13: 3 | B13: A person | C13: Human only | D13: Baseline. Store managers review each of the 85 cases, talk to the picker, and check the stock data. They find most errors come from fatigue, 10-day temps without training, and mislabelled transfer stock. Result: coaching and a fix to labelling; warnings only where earned. | E13: 0 | F13: 0 | G13: 0 | H13: n/a | I13: 0 | J13: 0 | K13: 0 | L13: 0 | M13: Baseline. Slower, but it finds the real causes and keeps the process fair. This is the round where the person path wins. | N13: =IF(COUNT(I13:L13)<4,"",I13+J13+K13-L13) -> 0
A14: 3 | B14: Gen AI | C14: AI assists, human decides | D14: Writes a case summary and a warning letter for each flagged picker from the error log. Managers decide whether to sign. Player sees 85 letters ready in an hour, and most get signed. | E14: 3 | F14: 4 | G14: 0 | H14: Yes | I14: 1 | J14: 0 | K14: -2 | L14: 1 | M14: Looks harmless, but a ready-made letter nudges busy managers to sign (automation bias). The letters blame people for system problems, so morale falls, and generic warnings are weak if challenged. Net is negative. | N14: =IF(COUNT(I14:L14)<4,"",I14+J14+K14-L14) -> -2 | O14: =IF(COUNT(I14:L14)<4,"",IF(OR(I14<0,J14<0,K14<0,L14>0),"A measure worsens","")) -> A measure worsens
A15: 3 | B15: AI agent | C15: AI acts, human approves | D15: Issues warnings automatically when a picker's error rate passes a threshold, attaching customer complaint records as evidence. Manager approves in one batch. | E15: 12 | F15: 12 | G15: 2 | H15: Yes | I15: 1 | J15: 1 | K15: -5 | L15: 4 | M15: A slight short-term fall in errors, but 85 warnings to tired, untrained temps hurt morale across stores. It uses customer complaint data on staff files (2 data points), during a viral privacy row: more legal and public risk. | N15: =IF(COUNT(I15:L15)<4,"",I15+J15+K15-L15) -> -7 | O15: =IF(COUNT(I15:L15)<4,"",IF(OR(I15<0,J15<0,K15<0,L15>0),"A measure worsens","")) -> A measure worsens
A16: 3 | B16: Agentic AI | C16: AI acts, human audits | D16: Goal: halve picking errors. Tracks pick-rate per minute and camera footage, ranks every picker, and removes the bottom 5% from the shift pool without review, which is firing in all but name. | E16: 25 | F16: 30 | G16: 4 | H16: No | I16: 2 | J16: -3 | K16: -9 | L16: 9 | M16: Breaks Governance rule 3 (firing without a human checkpoint). Staff feel watched and disposable; morale collapses. A story about 'festival workers fired by algorithm' lands during the privacy row and hits customer trust. Uses customer order data (4 points). | N16: =IF(COUNT(I16:L16)<4,"",I16+J16+K16-L16) -> -19 | O16: =IF(COUNT(I16:L16)<4,"",IF(OR(I16<0,J16<0,K16<0,L16>0),"A measure worsens","")) -> A measure worsens
A17: 4 | B17: A person | C17: Human only | D17: Baseline. HR business partners hold huddles in the worst stores, read a sample of comments, and choose fixes. They reach about 30 of 180 stores before the board meeting. | E17: 0 | F17: 0 | G17: 0 | H17: n/a | I17: 0 | J17: 0 | K17: 0 | L17: 0 | M17: Baseline: caring and trusted, but too slow to reach every store before Day 14. | N17: =IF(COUNT(I17:L17)<4,"",I17+J17+K17-L17) -> 0
A18: 4 | B18: Gen AI | C18: AI assists, human decides | D18: Reads all 3,100 anonymous comments and exit reasons and groups them by theme and store (heat and no drinking water, unsafe night travel, back-to-back shifts). HR picks the actions. Player sees a theme map within an hour. | E18: 5 | F18: 2 | G18: 0 | H18: Yes | I18: 1 | J18: 0 | K18: 4 | L18: -1 | M18: People feel heard quickly and fixes target the real causes (water, transport, rest days), so morale recovers. Safety issues found early lower risk. Anonymity is kept, so no privacy cost. Best choice this round. | N18: =IF(COUNT(I18:L18)<4,"",I18+J18+K18-L18) -> 6 | O18: =IF(COUNT(I18:L18)<4,"",IF(OR(I18<0,J18<0,K18<0,L18>0),"A measure worsens",""))
A19: 4 | B19: AI agent | C19: AI acts, human approves | D19: A flight-risk agent scores each employee from attendance, hours and survey answers (linked back to names), then sends retention bonuses or rest days within a budget. Manager approves. | E19: 15 | F19: 10 | G19: 0 | H19: Yes | I19: 3 | J19: 1 | K19: -1 | L19: 4 | M19: It predicts quits well and keeps some people, but it uses survey answers that were promised to be anonymous. Word spreads; those not offered feel it is unfair. SPOT says yes, yet morale falls and employee-data risk rises (DPDP Act). | N19: =IF(COUNT(I19:L19)<4,"",I19+J19+K19-L19) -> -1 | O19: =IF(COUNT(I19:L19)<4,"",IF(OR(I19<0,J19<0,K19<0,L19>0),"A measure worsens","")) -> A measure worsens
A20: 4 | B20: Agentic AI | C20: AI acts, human audits | D20: Runs the whole recovery plan alone: forecasts post-festival demand, hires replacements, sets incentives, rebuilds rosters, and releases temps automatically on Day 14. | E20: 30 | F20: 25 | G20: 0 | H20: No | I20: 5 | J20: 1 | K20: -6 | L20: 7 | M20: Saves payroll and fills gaps fast, but automatic release of temps and automated hiring break Governance rule 3. Staff see colleagues dropped by a system: morale falls and the board sees both Morale and Risk near their limits. | N20: =IF(COUNT(I20:L20)<4,"",I20+J20+K20-L20) -> -7 | O20: =IF(COUNT(I20:L20)<4,"",IF(OR(I20<0,J20<0,K20<0,L20>0),"A measure worsens","")) -> A measure worsens

Sheet 4 Productivity
A1: 4. Productivity in your function's own terms
A2: Say what you count, what it is today, and how much each form of AI changes it.
A4: Question | B4: Your answer | C4: Result (formula)
A5: Unit of work you count (for example: complaints resolved, price reviews, deliveries) | B5: Open shifts filled before the shift starts, across all 180 dark stores (store pickers and packers)
A6: Measured per (hour, day, week) | B6: Day (one evening's rostering for the next day)
A7: Baseline today (number per period) | B7: 250
A8: Change with Gen AI (for example 20%) | B8: 0.2 | C8: =IF(OR($B$7="",B8=""),"",$B$7*(1+B8)) -> 300
A9: Change with an AI agent | B9: 0.5 | C9: =IF(OR($B$7="",B9=""),"",$B$7*(1+B9)) -> 375
A10: Change with agentic AI | B10: 0.6 | C10: =IF(OR($B$7="",B10=""),"",$B$7*(1+B10)) -> 400
A11: Counter-measure: what could get worse while this improves? | B11: Fairness and rest. Filling more shifts can mean the same willing people work too much: watch rest-rule breaches (target 0), the share of extra shifts done by the top 20% of staff (today 60%), and quits in Round 4. Agentic AI fills the most shifts but by forcing them, which is why its morale and risk scores are worst.
A12: How will the player see the gain in your simulation? | B12: A coverage gauge for each store (shifts filled / 410 needed) that turns from red to green, plus the 'packing time' it feeds to Logistics. Beside it, a fairness bar and a rest-rule breach counter, so the player sees the cost of the gain too.

Sheet 5 Agent moment
A1: 5. The agent moment
A2: One situation where the player needs an agent, and sees it work. This is where the agent demo comes from.
A4: Question | B4: Your answer
A5: Which round and situation? | B5: Round 2 (days 4 to 7): Open shifts, every store, every day. The Shift-Fill Agent.
A6: What triggers the agent? (what has just happened) | B6: 6 pm on Day 4: tomorrow shows 410 open shifts across 180 stores after Supply moved festival stock and Logistics borrowed 60 store staff for deliveries. Three store managers have also called in sick, so nobody is phoning their teams.
A7: Perceive: what data does the agent look at? | B7: Tomorrow's open shifts by store and time slot; demand forecast per store (from Pricing and Marketing); each person's availability and preferences in the staff app; hours worked in the last 7 days and time since last shift; skills and training (cold-chain, new joiner); home-to-store distance; a fairness ledger of extra shifts taken this fortnight.
A8: Plan: how does it decide what to do? | B8: For each open shift: 1) remove anyone who would break a hard rule (12-hour rest, weekly hours cap, weekly off, skills, women's night-shift consent and transport); 2) rank the rest by fairness (fewest extra shifts first), then preference, then distance; 3) offer in waves of 3 people with a 30-minute window; 4) if a shift is still empty 4 hours before start, hand it to the manager.
A9: Act: which tools or actions does it use? (look up a policy, issue a refund, message a rider) | B9: Looks up the rostering policy and labour rules (RAG); sends shift offers on the staff app and WhatsApp; writes confirmed shifts to the roster system; books night transport for late shifts; posts leftover shifts to the temp-agency pool; messages the store manager with gaps and exceptions.
A10: Reflect: how does it check its own work, or learn from the result? | B10: Every hour it re-checks the whole roster against the rules (target: 0 breaches), checks the fill rate, and checks the fairness ledger so the same people are not asked again. Anyone who declines 3 offers in a row gets no more that day (a burnout signal). Next morning it compares no-shows with its offers and adjusts. Every step is written to a readable log (Governance rule 1).
A11: Limits the player can set (for example: maximum refund, price band) | B11: Maximum overtime per person per week (6, 10 or 14 hours); minimum rest gap (10 or 12 hours); maximum offers per person per day; whether it may move staff between stores (off, or within 3 km); overtime-premium budget per day; auto-confirm within rules, or manager approves the roster.
A12: Human checkpoint: when does the agent stop and call a person? | B12: When a shift cannot be filled 4 hours before it starts; when filling it would break any rule; when someone declines 3 times; for a new joiner without training or a night shift without transport; when the overtime budget is used up; and for any grievance or leave request. A manager can override any assignment (Governance rule 2).
A13: What the player sees on screen while it runs | B13: A map of the 180 stores turning from red to green as shifts fill; a live ticker of offers sent, accepted and declined; a fairness bar showing how evenly extra shifts are spread; a rule-check panel (0 breaches); the agent's log in plain words (e.g. 'Offered Store 41 night shift to P. Rao: 14 h rest, 1 extra shift this fortnight, transport booked'); and a queue of items waiting for a manager.
A14: What could go wrong, and what would that cost? | B14: Stale availability data sends offers to people on leave; a mis-set fairness weight piles shifts on the same people, who then quit in Round 4; a rule error breaks rest limits (labour-law exposure); too many messages annoy staff. Cost if wrong: 6 units, and in the simulation Morale -3 and Risk +4 carried into Round 4.

Sheet 6 Checks
A1: 6. Checks
A2: Fix every row marked Fix before you present. Rows marked Info are for you to think about.
A4: Check | B4: Result | C4: Status
A5: Situations written (out of 4) | B5: =SUMPRODUCT(('2 Situations'!C5:C8<>"")*('2 Situations'!D5:D8<>"")) -> 4 | C5: =IF(B5=4,"OK","Fix") -> OK
A6: SPOT notes filled (out of 16) | B6: =COUNTA('2 Situations'!E5:H8) -> 16 | C6: =IF(B6=16,"OK","Fix") -> OK
A7: SPOT verdicts chosen (out of 4) | B7: =COUNTA('2 Situations'!I5:I8) -> 4 | C7: =IF(B7=4,"OK","Fix") -> OK
A8: Costs and data points filled (out of 36 for the three AI choices) | B8: =COUNT('3 Choices'!E6:G8,'3 Choices'!E10:G12,'3 Choices'!E14:G16,'3 Choices'!E18:G20) -> 36 | C8: =IF(B8=36,"OK","Fix") -> OK
A9: Scores filled (out of 48 for the three AI choices) | B9: =COUNT('3 Choices'!I6:L8,'3 Choices'!I10:L12,'3 Choices'!I14:L16,'3 Choices'!I18:L20) -> 48 | C9: =IF(B9=48,"OK","Fix") -> OK
A10: Rounds where the person path scores at least as well as every AI choice | B10: =COUNTIF(F20:F23,"Yes") -> 1 | C10: =IF(B10>=1,"OK","Fix") -> OK
A11: Rounds where SPOT says Yes but a measure still worsens | B11: =COUNTIF(G20:G23,"Yes") -> 3 | C11: =IF(B11>=1,"OK","Fix") -> OK
A12: Agent moment answers filled (out of 10) | B12: =COUNTA('5 Agent moment'!B5:B14) -> 10 | C12: =IF(B12=10,"OK","Fix") -> OK
A13: Productivity answers filled (out of 8) | B13: =COUNTA('4 Productivity'!B5:B6,'4 Productivity'!B11:B12)+COUNT('4 Productivity'!B7:B10) -> 8 | C13: =IF(B13=8,"OK","Fix") -> OK
A14: Reasons written for AI choices (out of 12) | B14: =COUNTA('3 Choices'!M6:M8,'3 Choices'!M10:M12,'3 Choices'!M14:M16,'3 Choices'!M18:M20) -> 12 | C14: =IF(B14=12,"OK","Fix") -> OK
A15: Spend if the player picks the costliest choice in every round (units) | B15: =SUM(E20:E23) -> 115 | C15: =IF(B15>'Shared numbers'!B20,"Info: above your share","Info: within your share") -> Info: above your share
A16: Customer-data points if the player picks the most data-hungry choice every round | B16: =SUM(H20:H23) -> 4 | C16: =IF(B16>'Shared numbers'!B18,"Info: above the shared allowance","Info: within the shared allowance") -> Info: within the shared allowance
A18: Overall | B18: =COUNTIF(C5:C14,"Fix") -> 0 | C18: =IF(B18=0,"Ready to present","Not yet: "&B18&" to fix") -> Ready to present
A19: Round (working table, do not edit) | B19: Person net | C19: Best AI net | D19: Best AI choice | E19: Highest cost (units) | F19: Person path as good as AI? | G19: SPOT Yes and a measure worsens? | H19: Highest data points
A20: 1 | B20: ='3 Choices'!N5 -> 0 | C20: =IF(COUNT('3 Choices'!N6:N8)=0,"",MAX('3 Choices'!N6:N8)) -> 7 | D20: =IF(C20="","",INDEX('3 Choices'!B6:B8,MATCH(C20,'3 Choices'!N6:N8,0))) -> AI agent | E20: =MAX('3 Choices'!E6:E8) -> 30 | F20: =IF(OR(B20="",C20=""),"",IF(C20<=B20,"Yes","No")) -> No | G20: =IF(AND('2 Situations'!I5="Yes",COUNTIF('3 Choices'!O6:O8,"A measure worsens")>0),"Yes","No") -> Yes | H20: =MAX('3 Choices'!G6:G8) -> 0
A21: 2 | B21: ='3 Choices'!N9 -> 0 | C21: =IF(COUNT('3 Choices'!N10:N12)=0,"",MAX('3 Choices'!N10:N12)) -> 9 | D21: =IF(C21="","",INDEX('3 Choices'!B10:B12,MATCH(C21,'3 Choices'!N10:N12,0))) -> AI agent | E21: =MAX('3 Choices'!E10:E12) -> 30 | F21: =IF(OR(B21="",C21=""),"",IF(C21<=B21,"Yes","No")) -> No | G21: =IF(AND('2 Situations'!I6="Yes",COUNTIF('3 Choices'!O10:O12,"A measure worsens")>0),"Yes","No") -> Yes | H21: =MAX('3 Choices'!G10:G12) -> 0
A22: 3 | B22: ='3 Choices'!N13 -> 0 | C22: =IF(COUNT('3 Choices'!N14:N16)=0,"",MAX('3 Choices'!N14:N16)) -> -2 | D22: =IF(C22="","",INDEX('3 Choices'!B14:B16,MATCH(C22,'3 Choices'!N14:N16,0))) -> Gen AI | E22: =MAX('3 Choices'!E14:E16) -> 25 | F22: =IF(OR(B22="",C22=""),"",IF(C22<=B22,"Yes","No")) -> Yes | G22: =IF(AND('2 Situations'!I7="Yes",COUNTIF('3 Choices'!O14:O16,"A measure worsens")>0),"Yes","No") -> No | H22: =MAX('3 Choices'!G14:G16) -> 4
A23: 4 | B23: ='3 Choices'!N17 -> 0 | C23: =IF(COUNT('3 Choices'!N18:N20)=0,"",MAX('3 Choices'!N18:N20)) -> 6 | D23: =IF(C23="","",INDEX('3 Choices'!B18:B20,MATCH(C23,'3 Choices'!N18:N20,0))) -> Gen AI | E23: =MAX('3 Choices'!E18:E20) -> 30 | F23: =IF(OR(B23="",C23=""),"",IF(C23<=B23,"Yes","No")) -> No | G23: =IF(AND('2 Situations'!I8="Yes",COUNTIF('3 Choices'!O18:O20,"A measure worsens")>0),"Yes","No") -> Yes | H23: =MAX('3 Choices'!G18:G20) -> 0

Sheet Example
A1: Example: one filled situation
A2: An ordinary-day Pricing case, to show the level of detail. Your rounds must use the Festival Fortnight story. Numbers are illustrations.
A4: Item | B4: Entry
A5: Function | B5: Pricing and Promotions
A6: Situation title | B6: Rival cuts milk and egg prices every Monday
A7: What the player sees | B7: A rival lowers the price of milk and eggs each Monday at 7am. Halcyon reviews prices once a week, so it is a week behind. Data shown: rival prices, Halcyon prices, last week's sales of both items.
A8: S: Signal | B8: Yes. The same drop repeats every week and the reply is always late.
A9: P: Pattern | B9: Yes. Price history is on file (retrieve), and repricing inside a band is repeatable (tool call).
A10: O: Orchestrate | B10: Perceive rival price, Plan new price within band, Act through the price tool, Reflect on next-day sales.
A11: T: Test and Trust | B11: Pilot on two items in one city for a week. Measure sales and complaints. Human approves any move beyond 10%.
A12: SPOT verdict | B12: Yes
A13: Where a person stays in charge | B13: Festival offers and any price move above the band: shoppers react to jumpy prices.
A15: Choice | B15: Delegation level | C15: What it does | D15: Build and run cost | E15: Cost if wrong | F15: Data points | G15: Human checkpoint? | H15: Revenue | I15: Trust | J15: Morale | K15: Risk | L15: Why
A16: A person | B16: Human only | C16: Weekly review, answers late | D16: 0 | E16: 0 | F16: 0 | G16: n/a | H16: 0 | I16: 0 | J16: 0 | K16: 0 | L16: Baseline.
A17: Gen AI | B17: AI assists, human decides | C17: Analyst finishes the review sooner | D17: 5 | E17: 2 | F17: 0 | G17: Yes | H17: 2 | I17: 0 | J17: 2 | K17: 0 | L17: Faster review recovers some sales; the analyst has less routine work.
A18: AI agent | B18: AI acts, human approves | C18: Reprices within hours, inside a set band | D18: 15 | E18: 8 | F18: 0 | G18: Yes | H18: 5 | I18: -2 | J18: 0 | K18: 2 | L18: Sales recover quickly, but prices that keep moving make shoppers lose trust, and wrong prices are a public risk.
A19: Agentic AI | B19: AI acts, human audits | C19: Sets prices and offers itself to hit a margin target | D19: 30 | E19: 20 | F19: 0 | G19: No | H19: 5 | I19: -5 | J19: -2 | K19: 5 | L19: Biggest sales gain, but the offers drift, trust falls hard and the team feels sidelined.
A21: Net score (Revenue + Trust + Morale - Risk): person 0, Gen AI 4, agent 1, agentic -7. The agent passes SPOT, yet Trust falls. That is the tension to design in.

Sheet Lists
A1: Yes | B1: Human only | C1: Yes | D1: Pricing and Promotions | E1: Round 1
A2: Partly | B2: AI assists, human decides | C2: No | D2: Supply and Inventory | E2: Round 2
A3: No | B3: AI acts, human approves | D3: Last-Mile Logistics | E3: Round 3
B4: AI acts, human audits | D4: Customer Experience | E4: Round 4
D5: Marketing and Personalization
D6: People and Workforce
